hybrid_compute/__init__.py
hybrid_compute/__version__.py
hybrid_compute-0.0.5.dist-info/LICENSE
hybrid_compute-0.0.5.dist-info/METADATA
hybrid_compute-0.0.5.dist-info/WHEEL
hybrid_compute-0.0.5.dist-info/top_level.txt
hybrid_compute-0.0.5.dist-info/RECORD
