Metadata-Version: 2.2
Name: hybrid-compute
Version: 0.0.5
Summary: Easily and seemlessly work with cloud data on local compute resources
Home-page: https://github.com/fivetran/hybrid-compute
Author: Emrah Diril
Author-email: support@fivetran.com
Classifier: License :: OSI Approved :: Apache Software License
Classifier: Operating System :: Microsoft :: Windows
Classifier: Operating System :: MacOS :: MacOS X
Classifier: Operating System :: POSIX :: Linux
Classifier: Programming Language :: Python :: 3.10
Classifier: Programming Language :: Python :: 3.11
Classifier: Programming Language :: Python :: 3.12
Requires-Python: >=3.10
License-File: LICENSE
Requires-Dist: duckdb==1.2.0
Requires-Dist: sqlglot==26.6.0
Requires-Dist: simplekv==0.14.1
Requires-Dist: pyiceberg[duckdb]==0.8.1
Requires-Dist: pyarrow==18.1.0
Dynamic: author
Dynamic: author-email
Dynamic: classifier
Dynamic: description
Dynamic: description-content-type
Dynamic: home-page
Dynamic: requires-dist
Dynamic: requires-python
Dynamic: summary
